Workbook

Sheet Sheet1
A1: Apartment Number | B1: Nestaway-ID | C1: Lease Status | D1: Apartment Floor | E1: Apartment Type | F1: Rent Income Beneficiary | G1: Maintenance Cost | H1: Water Cost | I1: Rent Receivable
A2: 101 | B2: N35410 | C2: Leasable | D2: 1 | E2: 2BHK | F2: Mohammed Ashraf | G2: 1500 | H2: 800 | I2: 21000
A3: 102 | B3: N35260 | C3: Leasable | D3: 1 | E3: 2BHK | F3: Mohammed Abdurrahman | G3: 1500 | H3: 800 | I3: 21000
A4: 103 | B4: NA | C4: Non-Leasable | D4: 1 | E4: 3BHK | F4: N/A
A5: 201 | B5: N35259 | C5: Leasable | D5: 2 | E5: 2BHK | F5: Mohammed Abdurrahman | G5: 1500 | H5: 800 | I5: 21000
A6: 202 | B6: N35408 | C6: Leasable | D6: 2 | E6: 2BHK | F6: Mohammed Ashraf | G6: 1500 | H6: 800 | I6: 21000
A7: 203 | B7: N35404 | C7: Leasable | D7: 2 | E7: 1BHK | F7: Mohammed Afzal | G7: 1000 | H7: 500 | I7: 16000
A8: 204 | B8: N35405 | C8: Leasable | D8: 2 | E8: 1BHK | F8: Mohammed Afzal | G8: 1000 | H8: 500 | I8: 16000
A9: 301 | B9: N35261 | C9: Leasable | D9: 3 | E9: 2BHK | F9: Mohammed Afzal | G9: 1500 | H9: 800 | I9: 21000
A10: 302 | B10: N35409 | C10: Leasable | D10: 3 | E10: 2BHK | F10: Mohammed Ashraf | G10: 1500 | H10: 800 | I10: 21000
A11: 303 | B11: N35400 | C11: Leasable | D11: 3 | E11: 1BHK | F11: Ruksana Parveen | G11: 1000 | H11: 500 | I11: 16000
A12: 304 | B12: N35403 | C12: Leasable | D12: 3 | E12: 1BHK | F12: Mohammed Afzal | G12: 1000 | H12: 500 | I12: 16000
A13: 401 | B13: N35262 | C13: Leasable | D13: 4 | E13: 2BHK | F13: Mohammed Abdurrahman | G13: 1500 | H13: 800 | I13: 21000
A14: 402 | B14: N35407 | C14: Leasable | D14: 4 | E14: 1BHK | F14: Mohammed Anas | G14: 1000 | H14: 500 | I14: 16000
A15: 403 | B15: N35445 | C15: Leasable | D15: 4 | E15: 1BHK | F15: Mohammed Afzal | G15: 1000 | H15: 500 | I15: 16000
A16: 404 | B16: N35401 | C16: Leasable | D16: 4 | E16: 1BHK | F16: Ruksana Parveen | G16: 1000 | H16: 500 | I16: 16000
... A20: 504 | B20: N35468 | C20: Leasable | D20: 5 | E20: 1BHK | F20: Ruksana Parveen | G20: 1000 | H20: 500 | I20: 16000
A21: 601 | B21: NA | C21: Non-Leasable | D21: 6 | E21: 4BHK | F21: N/A

Sheet property_charges
A1: id | B1: flat_number | C1: nestaway_id | D1: charge_type | E1: amount | F1: effective_from | G1: effective_to
A2: 1 | B2: 101 | C2: =VLOOKUP(Table1[[#This Row],[flat_number]],Sheet1!$A$1:$B$21,2,FALSE) -> N35410 | D2: rent | E2: 21000 | F2: 45658
A3: 2 | B3: 102 | C3: =VLOOKUP(Table1[[#This Row],[flat_number]],Sheet1!$A$1:$B$21,2,FALSE) -> N35260 | D3: rent | E3: 21000 | F3: 45658
A4: 3 | B4: 103 | C4: =VLOOKUP(Table1[[#This Row],[flat_number]],Sheet1!$A$1:$B$21,2,FALSE) -> NA | D4: rent | E4: 0 | F4: 45658
A5: 4 | B5: 201 | C5: =VLOOKUP(Table1[[#This Row],[flat_number]],Sheet1!$A$1:$B$21,2,FALSE) -> N35259 | D5: rent | E5: 21000 | F5: 45658
A6: 5 | B6: 202 | C6: =VLOOKUP(Table1[[#This Row],[flat_number]],Sheet1!$A$1:$B$21,2,FALSE) -> N35408 | D6: rent | E6: 21000 | F6: 45658
A7: 6 | B7: 203 | C7: =VLOOKUP(Table1[[#This Row],[flat_number]],Sheet1!$A$1:$B$21,2,FALSE) -> N35404 | D7: rent | E7: 16000 | F7: 45658
A8: 7 | B8: 204 | C8: =VLOOKUP(Table1[[#This Row],[flat_number]],Sheet1!$A$1:$B$21,2,FALSE) -> N35405 | D8: rent | E8: 16000 | F8: 45658
A9: 8 | B9: 301 | C9: =VLOOKUP(Table1[[#This Row],[flat_number]],Sheet1!$A$1:$B$21,2,FALSE) -> N35261 | D9: rent | E9: 21000 | F9: 45658
A10: 9 | B10: 302 | C10: =VLOOKUP(Table1[[#This Row],[flat_number]],Sheet1!$A$1:$B$21,2,FALSE) -> N35409 | D10: rent | E10: 21000 | F10: 45658
A11: 10 | B11: 303 | C11: =VLOOKUP(Table1[[#This Row],[flat_number]],Sheet1!$A$1:$B$21,2,FALSE) -> N35400 | D11: rent | E11: 16000 | F11: 45658
A12: 11 | B12: 304 | C12: =VLOOKUP(Table1[[#This Row],[flat_number]],Sheet1!$A$1:$B$21,2,FALSE) -> N35403 | D12: rent | E12: 16000 | F12: 45658
A13: 12 | B13: 401 | C13: =VLOOKUP(Table1[[#This Row],[flat_number]],Sheet1!$A$1:$B$21,2,FALSE) -> N35262 | D13: rent | E13: 21000 | F13: 45658
... A61: 60 | B61: 601 | C61: =VLOOKUP(Table1[[#This Row],[flat_number]],Sheet1!$A$1:$B$21,2,FALSE) -> NA | D61: water_fee | E61: 0 | F61: 45658

Sheet Sheet2
A1: Expense Type | B1: Expense
A2: Utility | B2: Electrical Bill
A3: Utility | B3: Sweet Water Bill
A4: Utility | B4: WifI Bill
A5: Utility | B5: Trash Collection
A6: Utility | B6: Generator Diesel
A7: Utility | B7: General Building Maintenance
A8: Utility | B8: Water Tanker
A9: Utility | B9: Cleaning works
A10: Utility | B10: Other
A11: Operational | B11: Watchman Salary
A12: Operational | B12: Manager Salary
... A30: Guest Related | B30: Guest Hospitality Exp / Meal
